gucker/.arkitekt/.dockerignore
gucker/.arkitekt/.gitignore
gucker/__init__.py
gucker/api/schema.py
gucker/assets/idle.png
gucker/assets/idle_black.png
gucker/assets/logo.ico
gucker/assets/watching.png
gucker/assets/watching_black.png
gucker/env.py
gucker/main.py
gucker-0.1.1.dist-info/METADATA
gucker-0.1.1.dist-info/WHEEL
gucker-0.1.1.dist-info/entry_points.txt
gucker-0.1.1.dist-info/RECORD
